LICENSE.md
README.md
setup.cfg
setup.py
bin/tron
sdss_tron.egg-info/PKG-INFO
sdss_tron.egg-info/SOURCES.txt
sdss_tron.egg-info/dependency_links.txt
sdss_tron.egg-info/not-zip-safe
sdss_tron.egg-info/requires.txt
sdss_tron.egg-info/top_level.txt
tron/Auth.py
tron/__init__.py
tron/g.py
tron/hub.py
tron/listActors.py
tron/programs.json
tron/runhub.py
tron/Hub/__init__.py
tron/Hub/Command/Command.py
tron/Hub/Command/__init__.py
tron/Hub/Command/Decoders/ASCIICmdDecoder.py
tron/Hub/Command/Decoders/CommandDecoder.py
tron/Hub/Command/Decoders/RawCmdDecoder.py
tron/Hub/Command/Decoders/__init__.py
tron/Hub/Command/Encoders/ASCIICmdEncoder.py
tron/Hub/Command/Encoders/BinaryCmdEncoder.py
tron/Hub/Command/Encoders/CommandEncoder.py
tron/Hub/Command/Encoders/RawCmdEncoder.py
tron/Hub/Command/Encoders/__init__.py
tron/Hub/KV/KVDict.py
tron/Hub/KV/__init__.py
tron/Hub/Nub/ActorNub.py
tron/Hub/Nub/Commanders.py
tron/Hub/Nub/CoreNub.py
tron/Hub/Nub/Listeners.py
tron/Hub/Nub/NubAuth.py
tron/Hub/Nub/RawActorNub.py
tron/Hub/Nub/ShellNub.py
tron/Hub/Nub/SocketActorNub.py
tron/Hub/Nub/SocketCommanderNub.py
tron/Hub/Nub/TCCShellNub.py
tron/Hub/Nub/__init__.py
tron/Hub/Reply/FullReply.py
tron/Hub/Reply/Reply.py
tron/Hub/Reply/ReplyTaster.py
tron/Hub/Reply/__init__.py
tron/Hub/Reply/Decoders/ASCIIReplyDecoder.py
tron/Hub/Reply/Decoders/BinaryReplyDecoder.py
tron/Hub/Reply/Decoders/PyReplyDecoder.py
tron/Hub/Reply/Decoders/RawReplyDecoder.py
tron/Hub/Reply/Decoders/ReplyDecoder.py
tron/Hub/Reply/Decoders/__init__.py
tron/Hub/Reply/Encoders/ASCIIReplyEncoder.py
tron/Hub/Reply/Encoders/PyReplyEncoder.py
tron/Hub/Reply/Encoders/RawReplyEncoder.py
tron/Hub/Reply/Encoders/ReplyEncoder.py
tron/Hub/Reply/Encoders/__init__.py
tron/IO/Filehandler.py
tron/IO/IOHandler.py
tron/IO/PollAccept.py
tron/IO/PollConnect.py
tron/IO/PollHandler.py
tron/IO/ShellConnect.py
tron/IO/SocketHandler.py
tron/IO/__init__.py
tron/Misc/ID.py
tron/Misc/LLock.py
tron/Misc/Object.py
tron/Misc/__init__.py
tron/Misc/cdict.py
tron/Misc/cfg.py
tron/Misc/dates.py
tron/Misc/hub_log.py
tron/Misc/location.py
tron/Misc/logger.py
tron/Misc/qstr.py
tron/Misc/strcvt.py
tron/Misc/tback.py
tron/Misc/tcmd.py
tron/Misc/tqstr.py
